{"errors":[],"warnings":[],"namedChunkGroups":{"app":{"chunks":[3,1,2,0],"assets":["webpack-runtime-25a3448b63c96287a859.js","webpack-runtime-25a3448b63c96287a859.js.map","commons-4bda2cee8d9bbd52c2ad.js","commons-4bda2cee8d9bbd52c2ad.js.map","styles.5e5eb04b897791555070.css","styles-d723a74d179757f07678.js","styles-d723a74d179757f07678.js.map","app-6b044bf4a44d49e19aaf.js","app-6b044bf4a44d49e19aaf.js.map"],"children":{},"childAssets":{}},"component---src-templates-docs-js":{"chunks":[],"assets":[],"children":{},"childAssets":{}}},"assetsByChunkName":{"app":["webpack-runtime-25a3448b63c96287a859.js","commons-4bda2cee8d9bbd52c2ad.js","styles.5e5eb04b897791555070.css","styles-d723a74d179757f07678.js","app-6b044bf4a44d49e19aaf.js"],"component---src-templates-docs-js":[]}}